alu.v

/* 
 * ALU Verilog example (iverilog 10.1)
 *
 * Instruction set:
 * |---- OPCODE ----|         |----- OPERATION -----|
 * |     0b0000     |         |     out = a + b     |
 * |     0b0001     |         |     out = a - b     |
 * |     0b0010     |         |     out = a + 1     | 
 * |     0b0011     |         |     out = a - 1     |
 * |     0b0100     |         |     out = a << 1    |
 * |     0b0101     |         |     out = a >> 1    |
 * |     0b0110     |         | out = *rotate left* |
 * |     0b0111     |         | out = *rotate right*|
 * |     0b1000     |         |    out = A and B    |
 * |     0b1001     |         |    out = A or B     |
 * |     0b1010     |         |    out = A xor B    |
 * |     0b1011     |         |    out = A nor B    |
 * |     0b1100     |         |    out = A nand B   |
 * |     0b1101     |         |      out = ~ A      |
 * |     0b1110     |         |        *nop*        |
 * |     0b1111     |         |   *swap nibbles*    |
 *
 * Status register:
 * |-- BIT --|   |-- BIT NAME --|   |------------------------------- FUNCTION ------------------------------|
 * |    4    |   |      E       |   |  Equal flag     - A & B are equal                                     |            
 * |    3    |   |      Z       |   |  Zero flag      - the result of instruction equals 0                  |
 * |    2    |   |      C       |   |  Carry flag     - an arithmetic carry or borrow has been generated    |
 * |    1    |   |      P       |   |  Parity flag    - indicates if the number of set bits is odd or even  |
 * |    0    |   |      G       |   |  Compare flag   - (greater flag) if A => B => 1; A < B => 0;          | 
 */
 
 module alu
 (
     input  [7:0] a,b,
     input  [3:0] opcode,
     output [7:0] out,
     output [4:0] flags
 );

    reg  [8:0] result;
    reg  [4:0] status_reg;

    assign flags = status_reg;
    assign out = result[7:0];

    always @ (*)
    begin
        case (opcode)
            4'b0000:
                result = a + b;
            4'b0001:
                result = a - b;
            4'b0010:  
               result = a + 1;
            4'b0011:
                result = a - 1;
            4'b0100:
                result = {1'b0, a << 1};
            4'b0101:
                result = {1'b0, a >> 1};
            4'b0110:
                result = {a[6:0], a[7]};
            4'b0111:
                result = {a[0], a[7:1]};
            4'b1000:
                result = a & b;
            4'b1001:
                result = a | b;
            4'b1010:
                result = a ^ b;
            4'b1011:
                result = {1'b0, ~(a | b)};
            4'b1100:
                result = {1'b0, ~(a & b)};
            4'b1101:
                result = {1'b0, ~a};
            4'b1110:
                result = result;
            4'b1111:
                result = {a[3:0], a[7:4]};    
            default: 
                result = a;
        endcase

        /* if not NOP command */
        if (opcode != 4'b1110)
            begin
                /* carry/borrow flag */
                status_reg[2] <= result[8];

                /* equal flag */
                if (a == b)
                    status_reg[4] <= 1'b1;
                else
                    status_reg[4] <= 1'b0;

                /* zero flag */
                if (result == 0)
                    status_reg[3] <= 1'b1;
                else
                    status_reg[3] <= 1'b0; 

                /* parity flag */
                status_reg[1] = ~^result[7:0];

                /* compare flag */
                if (a >= b)
                    status_reg[0] <= 1'b1;
                else
                    status_reg[0] <= 1'b0;
            end
    end

endmodule

alu_tb.v
/* 
 * ALU Verilog example testbench (iverilog 10.1)
 */

`timescale 1ns/1ps

`include "alu.v"

module alu_tb;

    reg  [7:0] A, B;
    reg  [3:0] Opcode;
    wire [7:0] Out;
    wire [4:0] Flags;

    integer i;

    alu uut(.a(A), 
            .b(B), 
            .opcode(Opcode), 
            .out(Out), 
            .flags(Flags));

    initial
    begin

        $dumpfile("test.vcd");
        $dumpvars;

        $write("%c[1;35m",27); 
        $display("ALU testbench...\n");
        $write("%c[0m",27);

        $display("FLAGS [4:0]:");
        $display("|   4   |  3   |   2   |   1    |    0    |");
        $display("| EQUAL | ZERO | CARRY | PARITY | COMPARE |");

        $display("ADD:");
        Opcode = 0; 
        A = 36; 
        B = 58;
        #10;
        $display("A=%d, B=%d, Opcode=%d, Out=%d, Flags=%b \t\t%d\n", A, B, Opcode, Out, Flags, $time);

        $display("ADD + CARRY:");
        Opcode = 0; 
        A = 250; 
        B = 250;
        #10;
        $display("A=%d, B=%d, Opcode=%d, Out=%d, Flags=%b \t\t%d\n", A, B, Opcode, Out, Flags, $time);

        $display("SUBSTRACT:");
        Opcode = 1; 
        A = 137; 
        B = 26;
        #10;
        $display("A=%d, B=%d, Opcode=%d, Out=%d, Flags=%b \t\t%d\n", A, B, Opcode, Out, Flags, $time);

        $display("SUBSTRACT + CARRY:");
        Opcode = 1; 
        A = 26; 
        B = 137;
        #10;
        $display("A=%d, B=%d, Opcode=%d, Out=%d, Flags=%b \t\t%d\n", A, B, Opcode, Out, Flags, $time);

        $display("INCREMENT A:");
        Opcode = 2; 
        A = 68; 
        #10;
        $display("A=%d, Opcode=%d, Out=%d, Flags=%b \t\t\t%d\n", A, Opcode, Out, Flags, $time);

        $display("INCREMENT A + CARRY:");
        Opcode = 2; 
        A = 255; 
        #10;
        $display("A=%d, Opcode=%d, Out=%d, Flags=%b \t\t\t%d\n", A, Opcode, Out, Flags, $time);

        $display("DECREMENT A:");
        Opcode = 3; 
        A = 68; 
        #10;
        $display("A=%d, Opcode=%d, Out=%d, Flags=%b \t\t\t%d\n", A, Opcode, Out, Flags, $time);

        $display("DECREMENT A + CARRY:");
        Opcode = 3; 
        A = 0; 
        #10;
        $display("A=%d, Opcode=%d, Out=%d, Flags=%b \t\t\t%d\n", A, Opcode, Out, Flags, $time);

        $display("SHIFT A LEFT:");
        Opcode = 4; 
        A = 170; 
        #10;
        $display("A=%b, Opcode=%d, Out=%b, Flags=%b %d\t\t\n", A, Opcode, Out, Flags, $time);

        $display("SHIFT A RIGHT:");
        Opcode = 5; 
        A = 85; 
        #10;
        $display("A=%b, Opcode=%d, Out=%b, Flags=%b %d\t\t\n", A, Opcode, Out, Flags, $time);

        $display("ROTATE A LEFT:");
        Opcode = 6; 
        A = 170; 
        #10;
        $display("A=%b, Opcode=%d, Out=%b, Flags=%b %d\t\n", A, Opcode, Out, Flags, $time);

        $display("ROTATE A RIGHT:");
        Opcode = 7; 
        A = 85; 
        #10;
        $display("A=%b, Opcode=%d, Out=%b, Flags=%b %d\t\n", A, Opcode, Out, Flags, $time);

        $display("AND:");
        Opcode = 8; 
        A = 86; 
        B = 34;
        #10;
        $display("A=%b, B=%b, Opcode=%d, Out=%b, Flags=%b \t%d\n", A, B, Opcode, Out, Flags, $time);

        $display("OR:");
        Opcode = 9; 
        A = 86; 
        B = 34;
        #10;
        $display("A=%b, B=%b, Opcode=%d, Out=%b, Flags=%b \t%d\n", A, B, Opcode, Out, Flags, $time);

        $display("XOR:");
        Opcode = 10; 
        A = 86; 
        B = 34;
        #10;
        $display("A=%b, B=%b, Opcode=%d, Out=%b, Flags=%b \t%d\n", A, B, Opcode, Out, Flags, $time);

        $display("NOR:");
        Opcode = 11; 
        A = 86; 
        B = 34;
        #10;
        $display("A=%b, B=%b, Opcode=%d, Out=%b, Flags=%b \t%d\n", A, B, Opcode, Out, Flags, $time);

        $display("NAND:");
        Opcode = 12; 
        A = 86; 
        B = 34;
        #10;
        $display("A=%b, B=%b, Opcode=%d, Out=%b, Flags=%b \t%d\n", A, B, Opcode, Out, Flags, $time);

        $display("NEGATE A:");
        Opcode = 13; 
        A = 15; 
        #10;
        $display("A=%b, Opcode=%d, Out=%b, Flags=%b %d\t\n", A, Opcode, Out, Flags, $time);

        $display("NOP:");
        Opcode = 14; 
        #10;
        $display("A=%b, B=%b, Opcode=%d, Out=%b, Flags=%b \t%d\n", A, B, Opcode, Out, Flags, $time);

        $display("SWAP NIBBLES A:");
        Opcode = 15; 
        A = 90; 
        #10;
        $display("A=%b, Opcode=%d, Out=%b, Flags=%b %d\t\n", A, Opcode, Out, Flags, $time);

    end
endmodule

test.vcd
$date
	Tue Nov  6 02:35:43 2018
$end
$version
	Icarus Verilog
$end
$timescale
	1ps
$end
$scope module alu_tb $end
$var wire 8 ! Out [7:0] $end
$var wire 5 " Flags [4:0] $end
$var reg 8 # A [7:0] $end
$var reg 8 $ B [7:0] $end
$var reg 4 % Opcode [3:0] $end
$scope module uut $end
$var wire 8 & a [7:0] $end
$var wire 8 ' b [7:0] $end
$var wire 5 ( flags [4:0] $end
$var wire 4 ) opcode [3:0] $end
$var wire 8 * out [7:0] $end
$var reg 9 + result [8:0] $end
$var reg 5 , status_reg [4:0] $end
$upscope $end
$upscope $end
$enddefinitions $end
#0
$dumpvars
b0 ,
b1011110 +
b1011110 *
b0 )
b0 (
b111010 '
b100100 &
b0 %
b111010 $
b100100 #
b0 "
b1011110 !
$end
#10000
b10101 "
b10101 (
b10101 ,
b11110100 !
b11110100 *
b111110100 +
b11111010 $
b11111010 '
b11111010 #
b11111010 &
#20000
b1101111 !
b1101111 *
b11 "
b11 (
b11 ,
b1101111 +
b11010 $
b11010 '
b10001001 #
b10001001 &
b1 %
b1 )
#30000
b10010001 !
b10010001 *
b100 "
b100 (
b100 ,
b110010001 +
b10001001 $
b10001001 '
b11010 #
b11010 &
#40000
b0 "
b0 (
b0 ,
b1000101 !
b1000101 *
b1000101 +
b1000100 #
b1000100 &
b10 %
b10 )
#50000
b0 !
b0 *
b111 "
b111 (
b111 ,
b100000000 +
b11111111 #
b11111111 &
#60000
b1000011 !
b1000011 *
b0 "
b0 (
b0 ,
b1000011 +
b1000100 #
b1000100 &
b11 %
b11 )
#70000
b11111111 !
b11111111 *
b110 "
b110 (
b110 ,
b111111111 +
b0 #
b0 &
#80000
b1010100 !
b1010100 *
b1 "
b1 (
b1 ,
b1010100 +
b10101010 #
b10101010 &
b100 %
b100 )
#90000
b0 "
b0 (
b0 ,
b101010 !
b101010 *
b101010 +
b1010101 #
b1010101 &
b101 %
b101 )
#100000
b1010101 !
b1010101 *
b11 "
b11 (
b11 ,
b1010101 +
b10101010 #
b10101010 &
b110 %
b110 )
#110000
b10 "
b10 (
b10 ,
b10101010 !
b10101010 *
b10101010 +
b1010101 #
b1010101 &
b111 %
b111 )
#120000
b10 !
b10 *
b1 "
b1 (
b1 ,
b10 +
b100010 $
b100010 '
b1010110 #
b1010110 &
b1000 %
b1000 )
#130000
b1110110 !
b1110110 *
b1110110 +
b1001 %
b1001 )
#140000
b1110100 !
b1110100 *
b11 "
b11 (
b11 ,
b1110100 +
b1010 %
b1010 )
#150000
b10001001 !
b10001001 *
b1 "
b1 (
b1 ,
b10001001 +
b1011 %
b1011 )
#160000
b11111101 !
b11111101 *
b11111101 +
b1100 %
b1100 )
#170000
b11110000 !
b11110000 *
b10 "
b10 (
b10 ,
b11110000 +
b1111 #
b1111 &
b1101 %
b1101 )
#180000
b1110 %
b1110 )
#190000
b11 "
b11 (
b11 ,
b10100101 !
b10100101 *
b10100101 +
b1011010 #
b1011010 &
b1111 %
b1111 )
